Metadata-Version: 2.1
Name: nonebot_plugin_workscore
Version: 0.1.2
Summary: nonebot2 plugin work-score
Home-page: https://github.com/yzyyz1387/nonebot_plugin_workscore
Author: yzyyz1387
Author-email: youzyyz1384@qq.com
Keywords: pip,nonebot2,nonebot,workscore,nonebot_plugin
Platform: any
Classifier: Programming Language :: Python :: 3
Classifier: License :: OSI Approved :: MIT License
Classifier: Operating System :: OS Independent
License-File: LICENSE
Requires-Dist: requests
Requires-Dist: nonebot-adapter-onebot>=2.0.0-beta.1
Requires-Dist: nonebot2>=2.0.0-beta.1
Requires-Dist: httpx
